{
  "en": {
    "image": "https://i.ibb.co/qY02cGf2/image.png",
    "title": "🆕 Version 1.6.0 (204)",
    "text": "- Added Companions as separate grid tokens\n\n- Added an Action Bar for selected Tokens on grid\n\n- Tokens can now be selected and rotated\n\n- Features now can have Dice Rolls, and they can be tied to Custom Resources to automatically consume them\n\n- Added Currency as loot options for encounters\n\n- Fixed online grid Apply to Targets button when making an attack in some cases\n\n- Fixed the Initiative Tracker requiring tokens on the grid to add combatants\n\n- Fixed some online race conditions when syncing\n\n- Fixed Roll Initiative for All bug when having players connected to the room\n\n- Scenes now have Templates for characters, so you won't need to add live goblins to the scene before placing tokens on the grid\n\n- Features, Classes, Backgrounds etc. descriptions now have a cleaner display, with bold section headers and indentation\n\n- Fixed walls sometimes disappearing on grid\n\n- Fixed Loot not being given in some cases\n\n- Switched the Search Dialog functions. Tapping will select, the trailing icon opens the details\n\n- Fixed campaign characters not showing on the Initiative Tracker\n\n- Grid image elements and background image now can use URLs (like profile images, etc.)\n\n- Fixed Campaign Scenes not using the Campaign Notes\n\n- Added an info box when selecting skills on Character Creation\n\n- CAMPAIGNS CAN NOW BE IMPORTED FROM MARKDOWN FILES\n\n- Added new formulas to system, for things like Archery and Tough. The XML importer will automatically detect them and set the appropriate modifiers\n\n- Added a Credits section in the main screen's side menu\n\n- Attributes/Skills advantages given by Features/Items/Toggleables can now have sources to help identify the Source or another useful information"
  },
  "pt": {
    "image": "https://i.ibb.co/qY02cGf2/image.png",
    "title": "🆕 Versão 1.6.0 (204)",
    "text": "- Companheiros adicionados como tokens separados na grade\n\n- Adicionada uma Barra de Ação para Tokens selecionados na grade\n\n- Tokens agora podem ser selecionados e rotacionados\n\n- Feições agora podem ter Rolagens de Dados, e podem ser vinculadas a Recursos Customizados para consumi-los automaticamente\n\n- Adicionada Moeda como opção de saque em encontros\n\n- Corrigido o botão Aplicar aos Alvos da grade online ao realizar um ataque em alguns casos\n\n- Corrigido o Rastreador de Iniciativa que exigia tokens na grade para adicionar combatentes\n\n- Corrigidas algumas condições de corrida online ao sincronizar\n\n- Corrigido o bug de Rolar Iniciativa para Todos quando há jogadores conectados à sala\n\n- Cenas agora têm Templates de personagens, então você não precisará adicionar goblins ativos à cena antes de colocar tokens na grade\n\n- Descrições de Feições, Classes, Antecedentes etc. agora têm uma exibição mais limpa, com cabeçalhos de seção em negrito e indentação\n\n- Corrigidas paredes que às vezes desapareciam na grade\n\n- Corrigido o Saque que não era distribuído em alguns casos\n\n- Invertidas as funções dos Diálogos de Busca. Tocar seleciona, o ícone no final abre os detalhes\n\n- Corrigidos personagens de campanha que não apareciam no Rastreador de Iniciativa\n\n- Elementos de imagem na grade e imagem de fundo agora podem usar URLs (como imagens de perfil, etc.)\n\n- Corrigido Cenas de Campanha que não usavam as Notas da Campanha\n\n- Adicionada uma caixa de informações ao selecionar habilidades na Criação de Personagem\n\n- CAMPANHAS AGORA PODEM SER IMPORTADAS DE ARQUIVOS MARKDOWN\n\n- Adicionadas novas fórmulas ao sistema, para coisas como Archery e Tough. O importador XML irá detectá-las automaticamente e definir os modificadores apropriados\n\n- Adicionada uma seção de Créditos no menu lateral da tela principal\n\n- Vantagens em Atributos/Habilidades concedidas por Feições/Itens/Ativáveis agora podem ter fontes para ajudar a identificar a Origem ou outra informação útil"
  },
  "es": {
    "image": "https://i.ibb.co/qY02cGf2/image.png",
    "title": "🆕 Versión 1.6.0 (204)",
    "text": "- Compañeros añadidos como tokens separados en la cuadrícula\n\n- Añadida una Barra de Acción para Tokens seleccionados en la cuadrícula\n\n- Los tokens ahora pueden seleccionarse y rotarse\n\n- Los Rasgos ahora pueden tener Tiradas de Dados, y pueden vincularse a Recursos Personalizados para consumirlos automáticamente\n\n- Añadida Moneda como opción de botín en encuentros\n\n- Corregido el botón Aplicar a Objetivos de la cuadrícula en línea al realizar un ataque en algunos casos\n\n- Corregido el Rastreador de Iniciativa que requería tokens en la cuadrícula para añadir combatientes\n\n- Corregidas algunas condiciones de carrera en línea al sincronizar\n\n- Corregido el error de Tirar Iniciativa para Todos cuando hay jugadores conectados a la sala\n\n- Las Escenas ahora tienen Plantillas de personajes, por lo que no necesitarás añadir goblins activos a la escena antes de colocar tokens en la cuadrícula\n\n- Las descripciones de Rasgos, Clases, Trasfondos, etc. ahora tienen una visualización más limpia, con encabezados de sección en negrita y sangría\n\n- Corregidas paredes que a veces desaparecían en la cuadrícula\n\n- Corregido el Botín que no se entregaba en algunos casos\n\n- Invertidas las funciones de los Diálogos de Búsqueda. Tocar selecciona, el icono al final abre los detalles\n\n- Corregidos personajes de campaña que no aparecían en el Rastreador de Iniciativa\n\n- Los elementos de imagen en la cuadrícula y la imagen de fondo ahora pueden usar URLs (como imágenes de perfil, etc.)\n\n- Corregidas las Escenas de Campaña que no usaban las Notas de Campaña\n\n- Añadido un cuadro de información al seleccionar habilidades en la Creación de Personaje\n\n- LAS CAMPAÑAS AHORA PUEDEN IMPORTARSE DESDE ARCHIVOS MARKDOWN\n\n- Añadidas nuevas fórmulas al sistema, para cosas como Archery y Tough. El importador XML las detectará automáticamente y establecerá los modificadores apropiados\n\n- Añadida una sección de Créditos en el menú lateral de la pantalla principal\n\n- Las ventajas en Atributos/Habilidades otorgadas por Rasgos/Objetos/Activables ahora pueden tener fuentes para ayudar a identificar el Origen u otra información útil"
  },
  "pl": {
    "image": "https://i.ibb.co/qY02cGf2/image.png",
    "title": "🆕 Wersja 1.6.0 (204)",
    "text": "- Towarzysze dodani jako osobne tokeny na siatce\n\n- Dodano Pasek Akcji dla zaznaczonych Tokenów na siatce\n\n- Tokeny można teraz zaznaczać i obracać\n\n- Cechy mogą teraz mieć Rzuty Kostkami i mogą być powiązane z Zasobami Niestandardowymi, aby automatycznie je zużywać\n\n- Dodano Walutę jako opcję łupu w spotkaniach\n\n- Naprawiono przycisk Zastosuj do Celów w siatce online podczas ataku w niektórych przypadkach\n\n- Naprawiono Tracker Inicjatywy wymagający tokenów na siatce do dodawania uczestników walki\n\n- Naprawiono niektóre wyścigi sieciowe podczas synchronizacji\n\n- Naprawiono błąd Rzutu Inicjatywy dla Wszystkich, gdy gracze są połączeni z pokojem\n\n- Sceny mają teraz Szablony postaci, dzięki czemu nie musisz dodawać żywych goblinów do sceny przed umieszczeniem tokenów na siatce\n\n- Opisy Cech, Klas, Pochodzeń itp. mają teraz czystszy wygląd z pogrubionymi nagłówkami sekcji i wcięciami\n\n- Naprawiono ściany, które czasem znikały na siatce\n\n- Naprawiono Łup, który w niektórych przypadkach nie był przyznawany\n\n- Zamieniono funkcje Okien Wyszukiwania. Dotknięcie wybiera, ikona z boku otwiera szczegóły\n\n- Naprawiono postacie z kampanii, które nie pojawiały się w Trackerze Inicjatywy\n\n- Elementy graficzne na siatce i obrazy tła mogą teraz używać adresów URL (jak zdjęcia profilowe itp.)\n\n- Naprawiono Sceny Kampanii, które nie korzystały z Notatek Kampanii\n\n- Dodano okno informacyjne przy wyborze umiejętności podczas Tworzenia Postaci\n\n- KAMPANIE MOŻNA TERAZ IMPORTOWAĆ Z PLIKÓW MARKDOWN\n\n- Dodano nowe formuły do systemu, m.in. dla Łucznictwa i Twardości. Importer XML automatycznie je wykryje i ustawi odpowiednie modyfikatory\n\n- Dodano sekcję Zasługi w menu bocznym ekranu głównego\n\n- Zalety w Atrybutach/Umiejętnościach przyznawane przez Cechy/Przedmioty/Przełączniki mogą teraz mieć źródła, aby ułatwić identyfikację Źródła lub innych przydatnych informacji"
  },
  "it": {
    "image": "https://i.ibb.co/qY02cGf2/image.png",
    "title": "🆕 Versione 1.6.0 (204)",
    "text": "- Aggiunti i Compagni come token separati sulla griglia\n\n- Aggiunta una Barra delle Azioni per i Token selezionati sulla griglia\n\n- I token possono ora essere selezionati e ruotati\n\n- Le Caratteristiche possono ora avere Tiri di Dado, e possono essere collegate a Risorse Personalizzate per consumarle automaticamente\n\n- Aggiunta la Valuta come opzione di bottino negli incontri\n\n- Corretto il pulsante Applica ai Bersagli della griglia online durante un attacco in alcuni casi\n\n- Corretto il Tracker d'Iniziativa che richiedeva token sulla griglia per aggiungere combattenti\n\n- Corrette alcune race condition online durante la sincronizzazione\n\n- Corretto il bug Tira Iniziativa per Tutti quando ci sono giocatori connessi alla stanza\n\n- Le Scene hanno ora Modelli di personaggi, quindi non dovrai aggiungere goblin attivi alla scena prima di posizionare i token sulla griglia\n\n- Le descrizioni di Caratteristiche, Classi, Background, ecc. ora hanno una visualizzazione più pulita con intestazioni di sezione in grassetto e rientri\n\n- Corrette le pareti che a volte scomparivano dalla griglia\n\n- Corretto il Bottino che non veniva assegnato in alcuni casi\n\n- Invertite le funzioni delle Finestre di Ricerca. Toccare seleziona, l'icona laterale apre i dettagli\n\n- Corretti i personaggi della campagna che non apparivano nel Tracker d'Iniziativa\n\n- Gli elementi immagine sulla griglia e l'immagine di sfondo possono ora utilizzare URL (come immagini del profilo, ecc.)\n\n- Corrette le Scene della Campagna che non utilizzavano le Note della Campagna\n\n- Aggiunta una casella informativa nella selezione delle abilità durante la Creazione del Personaggio\n\n- LE CAMPAGNE POSSONO ORA ESSERE IMPORTATE DA FILE MARKDOWN\n\n- Aggiunte nuove formule al sistema, per cose come Arciere e Duro. L'importatore XML le rileverà automaticamente e imposterà i modificatori appropriati\n\n- Aggiunta una sezione Crediti nel menu laterale della schermata principale\n\n- I vantaggi in Attributi/Abilità concessi da Caratteristiche/Oggetti/Attivabili possono ora avere fonti per identificare la Fonte o altre informazioni utili"
  },
  "fr": {
    "image": "https://i.ibb.co/qY02cGf2/image.png",
    "title": "🆕 Version 1.6.0 (204)",
    "text": "- Ajout des Compagnons comme tokens séparés sur la grille\n\n- Ajout d'une Barre d'Actions pour les Tokens sélectionnés sur la grille\n\n- Les tokens peuvent maintenant être sélectionnés et pivotés\n\n- Les Aptitudes peuvent maintenant avoir des Lancers de Dés, et peuvent être liées à des Ressources Personnalisées pour les consommer automatiquement\n\n- Ajout de la Monnaie comme option de butin dans les rencontres\n\n- Correction du bouton Appliquer aux Cibles de la grille en ligne lors d'une attaque dans certains cas\n\n- Correction du Tracker d'Initiative qui nécessitait des tokens sur la grille pour ajouter des combattants\n\n- Correction de certaines conditions de course en ligne lors de la synchronisation\n\n- Correction du bug Lancer l'Initiative pour Tous lorsque des joueurs sont connectés à la salle\n\n- Les Scènes ont maintenant des Modèles de personnages, vous n'aurez donc plus besoin d'ajouter des gobelins actifs à la scène avant de placer des tokens sur la grille\n\n- Les descriptions des Aptitudes, Classes, Historiques, etc. ont maintenant un affichage plus propre, avec des en-têtes de section en gras et l'indentation\n\n- Correction des murs qui disparaissaient parfois sur la grille\n\n- Correction du Butin qui n'était pas distribué dans certains cas\n\n- Inversion des fonctions des Fenêtres de Recherche. Appuyer sélectionne, l'icône latérale ouvre les détails\n\n- Correction des personnages de campagne n'apparaissant pas dans le Tracker d'Initiative\n\n- Les éléments d'image sur la grille et l'image de fond peuvent maintenant utiliser des URLs (comme des images de profil, etc.)\n\n- Correction des Scènes de Campagne n'utilisant pas les Notes de Campagne\n\n- Ajout d'une boîte d'information lors de la sélection des compétences dans la Création de Personnage\n\n- LES CAMPAGNES PEUVENT MAINTENANT ÊTRE IMPORTÉES DEPUIS DES FICHIERS MARKDOWN\n\n- Ajout de nouvelles formules au système, pour des choses comme Tir à l'Arc et Robuste. L'importateur XML les détectera automatiquement et définira les modificateurs appropriés\n\n- Ajout d'une section Crédits dans le menu latéral de l'écran principal\n\n- Les avantages en Attributs/Compétences accordés par les Aptitudes/Objets/Activables peuvent maintenant avoir des sources pour aider à identifier la Source ou une autre information utile"
  },
  "Android": "Version 1.6.0 (204)",
  "Ios": "Version 1.6.0 (204)",
  "MacOS": "Version 1.6.0 (204)",
  "Windows": "Version 1.6.0 (205)",
  "Web": "Version 1.6.0 (205)",
  "Linux": "Version 1.6.0 (204)",
  "message": {
    "en": "A new official release is available! Update now for the best experience.",
    "pt": "Uma nova versão oficial está disponível! Atualize agora para a melhor experiência.",
    "es": "¡Hay una nueva versión oficial disponible! Actualiza ahora para la mejor experiencia.",
    "pl": "Dostępne jest nowe oficjalne wydanie! Zaktualizuj teraz, aby uzyskać najlepsze wrażenia.",
    "it": "È disponibile una nuova versione ufficiale! Aggiorna ora per la migliore esperienza.",
    "fr": "Une nouvelle version officielle est disponible ! Mettez à jour maintenant pour la meilleure expérience."
  },
  "date": "2026-03-25T12:00:00Z"
}